dailypublisherrevenue/__init__.py
dailypublisherrevenue/dailyrevenue.py
finaltesting-1.0.dist-info/METADATA
finaltesting-1.0.dist-info/WHEEL
finaltesting-1.0.dist-info/top_level.txt
finaltesting-1.0.dist-info/RECORD
